prolothar_common/__init__.py
prolothar_common/color_utils.py
prolothar_common/console_utils.py
prolothar_common/func_tools.py
prolothar_common/gviz_utils.py
prolothar_common/levenshtein.cp311-win_amd64.pyd
prolothar_common/levenshtein.cpp
prolothar_common/levenshtein.pxd
prolothar_common/levenshtein.pyx
prolothar_common/longest_common_sublists.cpp
prolothar_common/longest_common_subsequence.cp311-win_amd64.pyd
prolothar_common/longest_common_subsequence.cpp
prolothar_common/longest_common_subsequence.pyx
prolothar_common/math_utils.py
prolothar_common/mdl_utils.cp311-win_amd64.pyd
prolothar_common/mdl_utils.cpp
prolothar_common/mdl_utils.pxd
prolothar_common/mdl_utils.pyi
prolothar_common/mdl_utils.pyx
prolothar_common/pm4py_utils.py
prolothar_common/random_utils.py
prolothar_common/timeout.py
prolothar_common/clustering/__init__.py
prolothar_common/clustering/fuzzy_k_medoid.py
prolothar_common/clustering/k_medoid.py
prolothar_common/clustering/activities/__init__.py
prolothar_common/clustering/activities/activity_k_medoid.py
prolothar_common/clustering/traces/__init__.py
prolothar_common/clustering/traces/common.py
prolothar_common/clustering/traces/one_hot_activity_clustering.py
prolothar_common/clustering/traces/vector_based_clustering.py
prolothar_common/clustering/traces/clustering_algorithm/__init__.py
prolothar_common/clustering/traces/clustering_algorithm/vector_based.py
prolothar_common/clustering/traces/encoder/__init__.py
prolothar_common/clustering/traces/encoder/activity_one_hot_encoding.py
prolothar_common/clustering/traces/encoder/activity_sgt.py
prolothar_common/clustering/traces/encoder/encoder.py
prolothar_common/collections/__init__.py
prolothar_common/collections/list_utils.cp311-win_amd64.pyd
prolothar_common/collections/list_utils.cpp
prolothar_common/collections/list_utils.pyi
prolothar_common/collections/list_utils.pyx
prolothar_common/collections/set_similarity.py
prolothar_common/collections/tuple_utils.cp311-win_amd64.pyd
prolothar_common-6.1.0.dist-info/LICENSE
prolothar_common-6.1.0.dist-info/METADATA
prolothar_common-6.1.0.dist-info/WHEEL
prolothar_common-6.1.0.dist-info/top_level.txt
prolothar_common-6.1.0.dist-info/RECORD
