Metadata-Version: 2.1
Name: prolothar-common
Version: 6.1.0
Summary: algorithms for process mining and data mining on event sequences
Home-page: https://github.com/shs-it/prolothar-common
Author: Boris Wiegand
Author-email: boris.wiegand@stahl-holding-saar.de
License: GNU GENERAL PUBLIC LICENSE
Classifier: Programming Language :: Python :: 3
Classifier: Programming Language :: Python :: 3.10
License-File: LICENSE
Requires-Dist: scikit-learn <2.0.0
Requires-Dist: more-itertools <9,>=8.6.0
Requires-Dist: graphviz ==0.14
Requires-Dist: pandas <2.0.0,>1.0.0
Requires-Dist: frozendict ==2.3.0
Requires-Dist: pm4py ==2.2.19.1
Requires-Dist: psutil >=5.7.2
Requires-Dist: lru-dict ==1.1.6
Requires-Dist: seaborn ==0.11.1
Requires-Dist: sgt ==2.0.3
Requires-Dist: Cython
Requires-Dist: scipy
Provides-Extra: ray
Requires-Dist: ray[default] ; extra == 'ray'
